ElexonDataPortal/__init__.py
ElexonDataPortal/_nbdev.py
ElexonDataPortal/api.py
ElexonDataPortal/rebuild.py
ElexonDataPortal/dev/__init__.py
ElexonDataPortal/dev/clientgen.py
ElexonDataPortal/dev/clientprep.py
ElexonDataPortal/dev/docs.py
ElexonDataPortal/dev/nbdev.py
ElexonDataPortal/dev/orchestrator.py
ElexonDataPortal/dev/raw.py
ElexonDataPortal/dev/rawgen.py
ElexonDataPortal/dev/rdf.py
ElexonDataPortal/dev/specgen.py
ElexonDataPortal/dev/utils.py
ElexonDataPortal/vis/__init__.py
ElexonDataPortal/vis/curtailment.py
ElexonDataPortal/vis/ei.py
ElexonDataPortal/vis/gen.py
ElexonDataPortal/vis/lolp.py
ElexonDataPortal/vis/map.py
ElexonDataPortal-2.0.16.dist-info/LICENSE
ElexonDataPortal-2.0.16.dist-info/METADATA
ElexonDataPortal-2.0.16.dist-info/WHEEL
ElexonDataPortal-2.0.16.dist-info/top_level.txt
ElexonDataPortal-2.0.16.dist-info/RECORD
