Metadata-Version: 2.1
Name: ElexonDataPortal
Version: 2.0.16
Summary: UNKNOWN
Home-page: https://github.com/OSUKED/ElexonDataPortal
Author: Ayrton Bourn
Author-email: ayrtonbourn@outlook.com
License: UNKNOWN
Platform: UNKNOWN
Classifier: Programming Language :: Python :: 3
Requires-Python: >=3.6
License-File: LICENSE
Requires-Dist: pandas (>=1.2.0)
Requires-Dist: requests (>=2.25.0)
Requires-Dist: tqdm (>=4.61.0)
Requires-Dist: xmltodict (>=0.12.0)
Provides-Extra: dev
Requires-Dist: fastcore (==1.3.19) ; extra == 'dev'
Requires-Dist: jinja2 (>=3.0.0) ; extra == 'dev'
Requires-Dist: nbdev (==1.1.15) ; extra == 'dev'
Requires-Dist: typer (>=0.3.2) ; extra == 'dev'
Requires-Dist: pyyaml (>=5.4.1) ; extra == 'dev'
Requires-Dist: geopandas (>=0.9.0) ; extra == 'dev'
Requires-Dist: moepy (>=1.1.4) ; extra == 'dev'
Requires-Dist: croniter (>=1.0.15) ; extra == 'dev'
Requires-Dist: seaborn (>=0.11.1) ; extra == 'dev'
